shuvo/__init__.py
Shuvo-0.3.dist-info/METADATA
Shuvo-0.3.dist-info/WHEEL
Shuvo-0.3.dist-info/top_level.txt
Shuvo-0.3.dist-info/RECORD
