Metadata-Version: 2.1
Name: Shuvo
Version: 0.3
Summary: this is a simple pip modul and test
